at_8257/__init__.py
at_8257/at_datetime_utils.py
at_8257-0.0.2.dist-info/LICENSE.txt
at_8257-0.0.2.dist-info/METADATA
at_8257-0.0.2.dist-info/WHEEL
at_8257-0.0.2.dist-info/top_level.txt
at_8257-0.0.2.dist-info/RECORD
