Metadata-Version: 2.1
Name: at_8257
Version: 0.0.2
Summary: A small example package
Author-email: Mustufa <mustafasabuwala24@gmail.com>
Classifier: Programming Language :: Python :: 3
Classifier: License :: OSI Approved :: MIT License
Classifier: Operating System :: OS Independent
Requires-Python: >=3.7
License-File: LICENSE.txt
Requires-Dist: pytz
Requires-Dist: datetime
